aiohttp_send/__init__.py
aiohttp_send/send.py
aiohttp_send/version.py
aiohttp_send-0.0.6.dist-info/METADATA
aiohttp_send-0.0.6.dist-info/RECORD
aiohttp_send-0.0.6.dist-info/WHEEL
aiohttp_send-0.0.6.dist-info/top_level.txt
