Metadata-Version: 2.1
Name: aiohttp-send
Version: 0.0.6
Summary: Send file in for aiohttp.web (http server for asyncio)
Home-page: https://github.com/Trim21/aiohttp-send
Author: Trim21
Author-email: trim21me@gmail.com
License: MIT
Platform: UNKNOWN
Classifier: License :: OSI Approved :: MIT License
Classifier: Intended Audience :: Developers
Classifier: Programming Language :: Python
Classifier: Programming Language :: Python :: 3
Classifier: Programming Language :: Python :: 3.5
Classifier: Programming Language :: Python :: 3.6
Classifier: Programming Language :: Python :: 3.7
Classifier: Development Status :: 3 - Alpha
Classifier: Topic :: Internet :: WWW/HTTP
Classifier: Framework :: AsyncIO
Requires-Python: >=3.5.3
Requires-Dist: aiofiles
Requires-Dist: aiohttp (>=3.0.0)
